<reportInputTemplate>
    <title>Входной отчет</title>


    <filters>
        <filter>
            <type>SELECT</type>
            <label>Гос.-собственник:</label>
            <key>codeAdm</key>
            <paramOrderNum>1</paramOrderNum>
            <paramType>in</paramType>
            <paramDataType>12</paramDataType>
            <filterValues>
                <filterValue>
                    <label>все</label>
                    <paramValue>11</paramValue>
                </filterValue>
                <filterValue>
                    <label>чужие</label>
                    <paramValue>10</paramValue>
                </filterValue>
                <filterValue>
                    <label>РЖД</label>
                    <paramValue>20</paramValue>
                </filterValue>
                <filterValue>
                    <label>БЧ</label>
                    <paramValue>21</paramValue>
                </filterValue>
                <filterValue>
                    <label>УЗ</label>
                    <paramValue>22</paramValue>
                </filterValue>
                <filterValue>
                    <label>ЧФМ</label>
                    <paramValue>23</paramValue>
                </filterValue>
                <filterValue>
                    <label>ЛГ</label>
                    <paramValue>24</paramValue>
                </filterValue>
                <filterValue>
                    <label>ЛДЗ</label>
                    <paramValue>25</paramValue>
                </filterValue>
                <filterValue>
                    <label>ЭВР</label>
                    <paramValue>26</paramValue>
                </filterValue>
                <filterValue>
                    <label>КЗХ</label>
                    <paramValue>27</paramValue>
                </filterValue>
                <filterValue>
                    <label>ГР</label>
                    <paramValue>28</paramValue>
                </filterValue>
                <filterValue>
                    <label>УТИ</label>
                    <paramValue>29</paramValue>
                </filterValue>
                <filterValue>
                    <label>АЗ</label>
                    <paramValue>57</paramValue>
                </filterValue>
                <filterValue>
                    <label>АРМ</label>
                    <paramValue>58</paramValue>
                </filterValue>
                <filterValue>
                    <label>КРГ</label>
                    <paramValue>59</paramValue>
                </filterValue>
                <filterValue>
                    <label>ТЖД</label>
                    <paramValue>66</paramValue>
                </filterValue>
                <filterValue>
                    <label>ТРК</label>
                    <paramValue>67</paramValue>
                </filterValue>
            </filterValues>
        </filter>
        <filter>
            <type>SELECT</type>
            <label>Признак контейнера на подв. состав:</label>
            <key>contPriznak</key>
            <paramOrderNum>2</paramOrderNum>
            <paramType>in</paramType>
            <paramDataType>12</paramDataType>
            <filterValues>
                <filterValue>
                    <label>все</label>
                    <paramValue>0</paramValue>
                </filterValue>
                <filterValue>
                    <label>на "земле"</label>
                    <paramValue>1</paramValue>
                </filterValue>
                <filterValue>
                    <label>на вагоне</label>
                    <paramValue>2</paramValue>
                </filterValue>
                <filterValue>
                    <label>в поезде</label>
                    <paramValue>3</paramValue>
                </filterValue>
            </filterValues>
        </filter>
        <filter>
            <type>SELECT</type>
            <label>Способ разложения:</label>
            <key>tipRaz</key>
            <paramOrderNum>3</paramOrderNum>
            <paramType>in</paramType>
            <paramDataType>12</paramDataType>
            <filterValues>
                <filterValue>
                    <label>по типоразмерам</label>
                    <paramValue>1</paramValue>
                </filterValue>
                <filterValue>
                    <label>по отделениям</label>
                    <paramValue>4</paramValue>
                </filterValue>
            </filterValues>
        </filter>
        <filter>
            <type>HIDDEN</type>
            <key>P1</key>
            <paramOrderNum>4</paramOrderNum>
            <paramType>out</paramType>
            <paramDataType>5</paramDataType>
        </filter>
        <filter>
            <type>HIDDEN</type>
            <key>P2</key>
            <paramOrderNum>5</paramOrderNum>
            <paramType>out</paramType>
            <paramDataType>4</paramDataType>
        </filter>
    </filters>

    <tables>
        <table>
            <columns>
                <column>
                    <operator>
                        <operatorKey>column</operatorKey>
                        <arguments>
                            <argument>
                                <columnNumber>1</columnNumber>
                            </argument>
                        </arguments>
                    </operator>
                </column>
                <column>
                    <operator>
                        <operatorKey>column</operatorKey>
                        <arguments>
                            <argument>
                                <columnNumber>2</columnNumber>
                            </argument>
                        </arguments>
                    </operator>
                </column>
                <column>
                    <operator>
                        <operatorKey>column</operatorKey>
                        <arguments>
                            <argument>
                                <columnNumber>3</columnNumber>
                            </argument>
                        </arguments>
                    </operator>
                </column>
                <column>
                    <operator>
                        <operatorKey>column</operatorKey>
                        <arguments>
                            <argument>
                                <columnNumber>4</columnNumber>
                            </argument>
                        </arguments>
                    </operator>
                </column>
                <column>
                    <operator>
                        <operatorKey>column</operatorKey>
                        <arguments>
                            <argument>
                                <columnNumber>5</columnNumber>
                            </argument>
                        </arguments>
                    </operator>
                </column>
                <column>
                    <operator>
                        <operatorKey>column</operatorKey>
                        <arguments>
                            <argument>
                                <columnNumber>6</columnNumber>
                            </argument>
                        </arguments>
                    </operator>
                </column>
            </columns>
        </table>
    </tables>
</reportInputTemplate>