<reportOutputTemplate>
    <title>Выходной отчет</title>


    <tables>
        <table>
            <headers>
                <rows>
                    <row>
                        <headerCells>
                            <headerCell>
                                <rowspan>2</rowspan>
                                <colspan/>
                                <headerText>Станция сoвершения операции</headerText>
                                <headerKey/>
                            </headerCell>
                            <headerCell>
                                <rowspan>2</rowspan>
                                <colspan/>
                                <headerText>Индекс поезда</headerText>
                                <headerKey/>
                            </headerCell>
                            <headerCell>
                                <rowspan>2</rowspan>
                                <colspan/>
                                <headerText>Номер поезда</headerText>
                                <headerKey/>
                            </headerCell>
                            <headerCell>
                                <rowspan>2</rowspan>
                                <colspan/>
                                <headerText>Направ- ление</headerText>
                                <headerKey/>
                            </headerCell>
                            <headerCell>
                                <rowspan>2</rowspan>
                                <colspan/>
                                <headerText>Последняя операция с поездом</headerText>
                                <headerKey/>
                            </headerCell>
                            <headerCell>
                                <rowspan>1</rowspan>
                                <colspan>4</colspan>
                                <headerText>Дата и время прибытия, фактическое</headerText>
                                <headerKey/>
                            </headerCell>
                            <headerCell>
                                <rowspan>1</rowspan>
                                <colspan>4</colspan>
                                <headerText>Дата и время прибытия, по расписанию</headerText>
                                <headerKey/>
                            </headerCell>
                            <headerCell>
                                <rowspan>2</rowspan>
                                <colspan/>
                                <headerText>Кол-во вагонов</headerText>
                                <headerKey/>
                            </headerCell>
                            <headerCell>
                                <rowspan>2</rowspan>
                                <colspan/>
                                <headerText>Отклонение от графика (+/-), мин.</headerText>
                                <headerKey/>
                            </headerCell>
                        </headerCells>
                    </row>
                    <row>
                        <headerCells>
                            <headerCell>
                                <rowspan/>
                                <colspan>1</colspan>
                                <headerText>День</headerText>
                                <headerKey/>
                            </headerCell>
                            <headerCell>
                                <rowspan/>
                                <colspan>1</colspan>
                                <headerText>Месяц</headerText>
                                <headerKey/>
                            </headerCell>
                            <headerCell>
                                <rowspan/>
                                <colspan>1</colspan>
                                <headerText>Час</headerText>
                                <headerKey/>
                            </headerCell>
                            <headerCell>
                                <rowspan/>
                                <colspan>1</colspan>
                                <headerText>Мин</headerText>
                                <headerKey/>
                            </headerCell>
                            <headerCell>
                                <rowspan/>
                                <colspan>1</colspan>
                                <headerText>День</headerText>
                                <headerKey/>
                            </headerCell>
                            <headerCell>
                                <rowspan/>
                                <colspan>1</colspan>
                                <headerText>Месяц</headerText>
                                <headerKey/>
                            </headerCell>
                            <headerCell>
                                <rowspan/>
                                <colspan>1</colspan>
                                <headerText>Час</headerText>
                                <headerKey/>
                            </headerCell>
                            <headerCell>
                                <rowspan/>
                                <colspan>1</colspan>
                                <headerText>Мин</headerText>
                                <headerKey/>
                            </headerCell>
                        </headerCells>
                    </row>
                </rows>
            </headers>
        </table>
    </tables>

</reportOutputTemplate>